zconst/ConstError.py
zconst/__init__.py
zconst/const_base.py
zconst/const_decorator.py
zconst/const_metaclass.py
zconst-1.0.0.dist-info/METADATA
zconst-1.0.0.dist-info/RECORD
zconst-1.0.0.dist-info/WHEEL
zconst-1.0.0.dist-info/top_level.txt
